LICENSE.md
README.md
setup.py
rl_exp_utils.egg-info/PKG-INFO
rl_exp_utils.egg-info/SOURCES.txt
rl_exp_utils.egg-info/dependency_links.txt
rl_exp_utils.egg-info/requires.txt
rl_exp_utils.egg-info/top_level.txt
rl_utils/__init__.py
rl_utils/common/__init__.py
rl_utils/common/algos.py
rl_utils/common/core_utils.py
rl_utils/common/datasets.py
rl_utils/common/debug_utils.py
rl_utils/common/net_utils.py
rl_utils/common/running_mean_std.py
rl_utils/common/tile_images.py
rl_utils/common/viz_utils.py
rl_utils/envs/__init__.py
rl_utils/envs/env_creator.py
rl_utils/envs/registry.py
rl_utils/envs/wrappers.py
rl_utils/envs/pointmass/__init__.py
rl_utils/envs/pointmass/pointmass_env.py
rl_utils/envs/pointmass/pointmass_obstacle.py
rl_utils/envs/vec_env/__init__.py
rl_utils/envs/vec_env/dummy_vec_env.py
rl_utils/envs/vec_env/shmem_vec_env.py
rl_utils/envs/vec_env/subproc_vec_env.py
rl_utils/envs/vec_env/vec_env.py
rl_utils/envs/vec_env/vec_env_wrappers.py
rl_utils/envs/vec_env/vec_frame_stack.py
rl_utils/envs/vec_env/vec_monitor.py
rl_utils/launcher/__init__.py
rl_utils/launcher/__main__.py
rl_utils/launcher/eval_sys.py
rl_utils/launcher/run_exp.py
rl_utils/logging/__init__.py
rl_utils/logging/base_logger.py
rl_utils/logging/wb_logger.py
rl_utils/plotting/__init__.py
rl_utils/plotting/auto_bar.py
rl_utils/plotting/auto_line.py
rl_utils/plotting/auto_table.py
rl_utils/plotting/utils.py
rl_utils/plotting/wb_query.py
tests/__init__.py
tests/test_auto_line.py
tests/test_launcher.py
tests/test_logger.py
tests/test_pointmass.py